docling_extractor/__init__.py
docling_extractor/extractor.py
docling_extractor-1.0.0.dist-info/licenses/LICENSE
docling_extractor-1.0.0.dist-info/METADATA
docling_extractor-1.0.0.dist-info/WHEEL
docling_extractor-1.0.0.dist-info/top_level.txt
docling_extractor-1.0.0.dist-info/RECORD
