Metadata-Version: 2.4
Name: docling-extractor
Version: 1.0.0
Summary: Production-grade document extraction with intelligent fallback chain: Docling -> PyMuPDF -> pdfplumber -> Tesseract
Author-email: Nalini Panwar <panwarnalini@gmail.com>
Maintainer-email: Nalini Panwar <panwarnalini@gmail.com>
License: MIT
Project-URL: Homepage, https://github.com/panwarnalini-hub/clinical-doc-pipelines
Project-URL: Documentation, https://github.com/panwarnalini-hub/clinical-doc-pipelines/blob/main/README.md
Project-URL: Repository, https://github.com/panwarnalini-hub/clinical-doc-pipelines
Project-URL: Bug Tracker, https://github.com/panwarnalini-hub/clinical-doc-pipelines/issues
Keywords: document-extraction,pdf-processing,docling,ocr,data-engineering,clinical-trials,nlp,databricks
Classifier: Development Status :: 4 - Beta
Classifier: Intended Audience :: Developers
Classifier: Intended Audience :: Science/Research
Classifier: License :: OSI Approved :: MIT License
Classifier: Operating System :: OS Independent
Classifier: Programming Language :: Python :: 3
Classifier: Programming Language :: Python :: 3.8
Classifier: Programming Language :: Python :: 3.9
Classifier: Programming Language :: Python :: 3.10
Classifier: Programming Language :: Python :: 3.11
Classifier: Programming Language :: Python :: 3.12
Classifier: Topic :: Scientific/Engineering
Classifier: Topic :: Text Processing
Classifier: Topic :: Software Development :: Libraries :: Python Modules
Requires-Python: >=3.8
License-File: LICENSE
Requires-Dist: PyMuPDF>=1.23.0
Requires-Dist: pdfplumber>=0.10.0
Provides-Extra: full
Requires-Dist: docling>=2.0.0; extra == "full"
Requires-Dist: docling-core>=2.0.0; extra == "full"
Requires-Dist: pytesseract>=0.3.10; extra == "full"
Provides-Extra: dev
Requires-Dist: pytest>=7.0.0; extra == "dev"
Requires-Dist: black>=23.0.0; extra == "dev"
Requires-Dist: isort>=5.12.0; extra == "dev"
Dynamic: license-file
